fenerbahce/__init__.py
fenerbahce/crawler.py
fenerbahce/interface.py
fenerbahce/last_match.py
fenerbahce/live.py
fenerbahce/next_match.py
fenerbahce-0.2.0.dist-info/entry_points.txt
fenerbahce-0.2.0.dist-info/WHEEL
fenerbahce-0.2.0.dist-info/METADATA
fenerbahce-0.2.0.dist-info/RECORD
