Metadata-Version: 2.1
Name: fenerbahce
Version: 0.2.0
Summary: 
Author: mehmet
Author-email: mehmetccm@gmail.com
Requires-Python: >=3.9,<4.0
Classifier: Programming Language :: Python :: 3
Classifier: Programming Language :: Python :: 3.9
Classifier: Programming Language :: Python :: 3.10
Classifier: Programming Language :: Python :: 3.11
Requires-Dist: bs4 (>=0.0.1,<0.0.2)
Requires-Dist: click (>=8.1.3,<9.0.0)
Requires-Dist: click-help-colors (>=0.9.1,<0.10.0)
Requires-Dist: colorama (>=0.4.5,<0.5.0)
Requires-Dist: coverage (>=6.5.0,<7.0.0)
Requires-Dist: lxml (>=4.9.1,<5.0.0)
Requires-Dist: pytest (>=7.1.3,<8.0.0)
Requires-Dist: requests (>=2.28.1,<3.0.0)
